etils/__init__.py
etils/array_types/__init__.py
etils/eapp/__init__.py
etils/eapp/dataclass_flags.py
etils/eapp/logging_utils.py
etils/ecolab/__init__.py
etils/ecolab/adhoc_error.py
etils/ecolab/array_as_img.py
etils/ecolab/auto_display_utils.py
etils/ecolab/cell_autoreload.py
etils/ecolab/colab_utils.py
etils/ecolab/highlight_util.py
etils/ecolab/inplace_reload.py
etils/ecolab/ip_utils.py
etils/ecolab/lazy_imports.py
etils/ecolab/lazy_utils.py
etils/ecolab/mock_colab.py
etils/ecolab/patch_utils.py
etils/ecolab/adhoc_lib/module_deps_utils.py
etils/ecolab/adhoc_lib/reload_workspace_lib.py
etils/ecolab/inspects/__init__.py
etils/ecolab/inspects/attrs.py
etils/ecolab/inspects/auto_utils.py
etils/ecolab/inspects/core.py
etils/ecolab/inspects/html_helper.py
etils/ecolab/inspects/nodes.py
etils/ecolab/inspects/resource_utils.py
etils/ecolab/inspects/static/auto_activate.css
etils/ecolab/inspects/static/auto_activate.js
etils/ecolab/inspects/static/main.js
etils/ecolab/inspects/static/theme.css
etils/ecolab/pyjs_com/__init__.py
etils/ecolab/pyjs_com/py_js_com.js
etils/ecolab/pyjs_com/py_js_com.py
etils/ecolab/static/highlight.css
etils/edc/__init__.py
etils/edc/cast_utils.py
etils/edc/context.py
etils/edc/dataclass_utils.py
etils/edc/field_utils.py
etils/edc/frozen_utils.py
etils/edc/helpers.py
etils/enp/__init__.py
etils/enp/array_spec.py
etils/enp/checking.py
etils/enp/compat.py
etils/enp/einops_utils.py
etils/enp/geo_utils.py
etils/enp/interp_utils.py
etils/enp/linalg.py
etils/enp/numpy_utils.py
etils/enp/testing.py
etils/enp/type_parsing.py
etils/enp/typing.py
etils/enp/array_types/__init__.py
etils/enp/array_types/dtypes.py
etils/enp/array_types/typing.py
etils/epath/__init__.py
etils/epath/abstract_path.py
etils/epath/backend.py
etils/epath/flags.py
etils/epath/gpath.py
etils/epath/register.py
etils/epath/resource_utils.py
etils/epath/stat_utils.py
etils/epath/testing.py
etils/epath/typing.py
etils/epy/__init__.py
etils/epy/_internal.py
etils/epy/_multiprocess.py
etils-1.12.1.dist-info/licenses/LICENSE
etils-1.12.1.dist-info/WHEEL
etils-1.12.1.dist-info/METADATA
etils-1.12.1.dist-info/RECORD
